<?xml version="1.0" encoding="utf-8" ?>
<LanguageData>
    
    <MechanoidFullyFormed.label>t채ysikasvuinen</MechanoidFullyFormed.label>
    
    <HumanlikeBaby.label>vauva</HumanlikeBaby.label>
    
    <HumanlikeToddler.label>taapero</HumanlikeToddler.label>
    
    <HumanlikeChild.label>lapsi</HumanlikeChild.label>
    
    <HumanlikeTeenager.label>teini-ik채inen</HumanlikeTeenager.label>
    
    <HumanlikeAdult.label>aikuinen</HumanlikeAdult.label>
    
    <EusocialInsectLarva.label>toukka</EusocialInsectLarva.label>
    
    <EusocialInsectJuvenile.label>ep채kyps채</EusocialInsectJuvenile.label>
    
    <EusocialInsectAdult.label>aikuinen</EusocialInsectAdult.label>
    
    <AnimalBaby.label>vauva</AnimalBaby.label>
    
    <AnimalJuvenile.label>pentu</AnimalJuvenile.label>
    
    <AnimalAdult.label>aikuinen</AnimalAdult.label>
    
</LanguageData>
