<?xml version="1.0" encoding="utf-8" ?>
<LanguageData>
    
    <Inspect.label>tarkasta</Inspect.label>
    
    <Architect.label>arkkitehti</Architect.label>
    <Architect.description>Määrää minne ja mitä yhdyskuntalaisten tulisi rakentaa, viljellä, varastoida ja niin edespäin.</Architect.description>
    
    <Work.label>työnteko</Work.label>
    <Work.description>Valitse kuka yhdyskuntalainen tekee minkälaista työtä ja missä tärkeysjärjestyksessä.</Work.description>
    
    <Restrictions.label>rajoitukset</Restrictions.label>
    <Restrictions.description>Rajoita yhdyskuntalaisia tiettyihin toimiin tiettyyn aikaan päivästä tai tiettyihin salittuihin alueisiin.</Restrictions.description>
    
    <Outfits.label>vaatekerrat</Outfits.label>
    <Outfits.description>Määritä mitä kukin yhdyskuntalainen saa pitää yllään.</Outfits.description>
    
    <Animals.label>eläimet</Animals.label>
    <Animals.description>Määritä miten yhdyskunnan kesyjä eläimiä kohdellaan.</Animals.description>
    
    <Factions.label>ryhmät</Factions.label>
    <Factions.description>Käy läpi yhdyskunnan tuntemat ryhmät ja niiden suhteet.</Factions.description>
    
    <World.label>maailma</World.label>
    <World.description>Tutki maailman karttaa.</World.description>
    
    <History.label>historia</History.label>
    <History.description>Käy läpi tietoja yhdyskunnan historiasta.</History.description>
    
    <Statistics.label>tilastotiedot</Statistics.label>
    <Statistics.description>Käy läpi tilastotietoja yhdyskunnasta.</Statistics.description>
    
    <Research.label>tutkimus</Research.label>
    <Research.description>Tarkastele ja päätä tutkimusprojekteista.</Research.description>
    
    <Menu.label>valikko</Menu.label>
    <Menu.description>Vaihda asetuksia, tallenna, lataa tai lopeta peli.</Menu.description>
    
</LanguageData>
